docs/sphinx/source/conf.py
smartsheet_engine/__init__.py
smartsheet_engine/client.py
smartsheet_engine/grids.py
smartsheet_engine/main.py
smartsheet_engine/utils.py
tests/test_client.py
tests/test_data.py
tests/test_grids.py
tests/test_smartsheet_engine.py
tests/test_utils.py
smartsheet_engine-1.5.0.dist-info/METADATA
smartsheet_engine-1.5.0.dist-info/WHEEL
smartsheet_engine-1.5.0.dist-info/entry_points.txt
smartsheet_engine-1.5.0.dist-info/top_level.txt
smartsheet_engine-1.5.0.dist-info/RECORD
