Metadata-Version: 2.1
Name: smartsheet_engine
Version: 1.5.0
Summary: A Python library that simplifies Smartsheet API workflows
Author-email: Nick OMalley <nickpeteromalley@gmail.com>
Project-URL: Homepage, https://github.com/1npo/smartsheet-engine
Keywords: smartsheet,smartsheet library
Classifier: License :: OSI Approved :: MIT License
Classifier: Programming Language :: Python
Classifier: Programming Language :: Python :: 3
Requires-Python: >=3.9
Requires-Dist: pandas
Requires-Dist: smartsheet-python-sdk
